logcli/__init__.py
logcli/main.py
logcli/utils/__init__.py
logcli/utils/auth.py
logcli/utils/config.py
logcli/utils/logs.py
logcli-0.1.1.dist-info/METADATA
logcli-0.1.1.dist-info/WHEEL
logcli-0.1.1.dist-info/entry_points.txt
logcli-0.1.1.dist-info/top_level.txt
logcli-0.1.1.dist-info/RECORD
