Metadata-Version: 2.1
Name: logcli
Version: 0.1.1
Summary: UNKNOWN
Home-page: UNKNOWN
Author: UNKNOWN
Author-email: UNKNOWN
License: UNKNOWN
Platform: UNKNOWN
Requires-Dist: requests
Requires-Dist: click
Requires-Dist: rich
Requires-Dist: argparse
